skippy_cov/__init__.py
skippy_cov/__main__.py
skippy_cov/config_handler.py
skippy_cov/diff_handler.py
skippy_cov/plugin.py
skippy_cov/tests_finder.py
skippy_cov/utils.py
skippy_cov-0.2.2.dist-info/entry_points.txt
skippy_cov-0.2.2.dist-info/licenses/LICENSE
skippy_cov-0.2.2.dist-info/WHEEL
skippy_cov-0.2.2.dist-info/METADATA
skippy_cov-0.2.2.dist-info/RECORD
