Metadata-Version: 2.4
Name: skippy-cov
Version: 0.2.2
Summary: Selectively run tests based on the current git diff and the collected data from previous tests runs
Keywords: python
Author-email: Mariano Garcia Berrotaran <mariano.garciaberrotaran@shiphero.com>, Martín Gaitán <marting@shiphero.com>
Requires-Python: >=3.8,<4.0
Classifier: Intended Audience :: Developers
Classifier: Programming Language :: Python
Classifier: Programming Language :: Python :: 3
Classifier: Programming Language :: Python :: 3.8
Classifier: Programming Language :: Python :: 3.9
Classifier: Programming Language :: Python :: 3.10
Classifier: Programming Language :: Python :: 3.11
Classifier: Programming Language :: Python :: 3.12
Classifier: Programming Language :: Python :: 3.13
Classifier: Topic :: Software Development :: Libraries :: Python Modules
License-File: LICENSE
Requires-Dist: unidiff >=0.7.5
Requires-Dist: coverage>=7.6
Requires-Dist: tomli; python_version < '3.11'
Project-URL: Repository, https://github.com/shiphero/skippy-cov
